tortfunc/__init__.py
tortfunc/exceptions.py
tortfunc/registry.py
tortfunc/retry.py
tortfunc/timeout/__init__.py
tortfunc/timeout/async_timeout.py
tortfunc/timeout/thread_timeout.py
tortfunc/types.py
tortfunc-1.1.0.dist-info/LICENSE
tortfunc-1.1.0.dist-info/WHEEL
tortfunc-1.1.0.dist-info/METADATA
tortfunc-1.1.0.dist-info/RECORD
